pynabi/__init__.py
pynabi/_common.py
pynabi/_dataset.py
pynabi/calculation.py
pynabi/crystal.py
pynabi/kspace.py
pynabi/occupation.py
pynabi/relaxation.py
pynabi/units.py
pynabi-0.1.2.dist-info/LICENSE
pynabi-0.1.2.dist-info/METADATA
pynabi-0.1.2.dist-info/WHEEL
pynabi-0.1.2.dist-info/top_level.txt
pynabi-0.1.2.dist-info/RECORD
