Metadata-Version: 2.1
Name: pynabi
Version: 0.1.2
Summary: A package to easily create Abinit input files
Author: Federico Guglielmi
License: MIT License
Project-URL: Homepage, https://github.com/Fedesky25/pynabi
Project-URL: Bug Tracker, https://github.com/Fedesky25/pynabi/issues
Project-URL: Documentation, https://github.com/Fedesky25/pynabi/wiki
Project-URL: Repository, https://github.com/Fedesky25/pynabi.git
Project-URL: Changelog, https://github.com/Fedesky25/pynabi/blob/master/CHANGELOG.md
Keywords: abinit
Classifier: Programming Language :: Python :: 3
Classifier: Programming Language :: Python :: 3.11
Classifier: Programming Language :: Python :: 3.12
Classifier: License :: OSI Approved :: MIT License
Classifier: Operating System :: OS Independent
Classifier: Intended Audience :: Science/Research
Classifier: Topic :: Scientific/Engineering :: Physics
Classifier: Topic :: Scientific/Engineering :: Chemistry
Requires-Python: >=3.11
License-File: LICENSE
